rtl/smart_light.v
module smart_light(
    input clk,
    input reset,
    input [7:0] sensor,
    output reg led
);

parameter THRESHOLD = 8'd100;

parameter OFF = 1'b0;
parameter ON  = 1'b1;

reg state, next_state;

// State Register
always @(posedge clk or posedge reset)
begin
    if(reset)
        state <= OFF;
    else
        state <= next_state;
end

// Next-State Logic
always @(*)
begin
    case(state)

        OFF:
        begin
            if(sensor < THRESHOLD)
                next_state = ON;
            else
                next_state = OFF;
        end

        ON:
        begin
            if(sensor < THRESHOLD)
                next_state = ON;
            else
                next_state = OFF;
        end

    endcase
end

// Output Logic (Moore FSM)
always @(*)
begin
    case(state)

        OFF: led = 0;
        ON : led = 1;

    endcase
end

endmodule

testbench/tb_smart_light.v
`timescale 1ns/1ps

module tb_smart_light;

reg clk;
reg reset;
reg [7:0] sensor;
wire led;

// Instantiate the DUT (Device Under Test)
smart_light uut (
    .clk(clk),
    .reset(reset),
    .sensor(sensor),
    .led(led)
);

// Clock generation (10 ns period)
always #5 clk = ~clk;

initial begin
    // Generate VCD file for GTKWave
    $dumpfile("smart_light.vcd");
    $dumpvars(0, tb_smart_light);

    clk = 0;
    reset = 1;
    sensor = 150;

    #10 reset = 0;

    // Bright -> LED OFF
    sensor = 150;
    #20;

    // Dark -> LED ON
    sensor = 80;
    #20;

    // Still Dark -> LED ON
    sensor = 50;
    #20;

    // Bright -> LED OFF
    sensor = 170;
    #20;

    // Bright -> LED OFF
    sensor = 250;
    #20;

    // Dark -> LED ON
    sensor = 60;
    #20;

    $finish;
end

endmodule

simulation/smart_light.vcd
$date
	Sun Jul 19 23:22:49 2026
$end
$version
	Icarus Verilog
$end
$timescale
	1ps
$end
$scope module tb_smart_light $end
$var wire 1 ! led $end
$var reg 1 " clk $end
$var reg 1 # reset $end
$var reg 8 $ sensor [7:0] $end
$scope module uut $end
$var wire 1 " clk $end
$var wire 1 # reset $end
$var wire 8 % sensor [7:0] $end
$var reg 1 ! led $end
$var reg 1 & next_state $end
$var reg 1 ' state $end
$upscope $end
$upscope $end
$enddefinitions $end
#0
$dumpvars
0'
0&
b10010110 %
b10010110 $
1#
0"
0!
$end
#5000
1"
#10000
0"
0#
#15000
1"
#20000
0"
#25000
1"
#30000
1&
0"
b1010000 $
b1010000 %
#35000
1!
1'
1"
#40000
0"
#45000
1"
#50000
0"
b110010 $
b110010 %
#55000
1"
#60000
0"
#65000
1"
#70000
0&
0"
b10101010 $
b10101010 %
#75000
0!
0'
1"
#80000
0"
#85000
1"
#90000
0"
b11111010 $
b11111010 %
#95000
1"
#100000
0"
#105000
1"
#110000
1&
0"
b111100 $
b111100 %
#115000
1!
1'
1"
